jwt_signature_validator/__init__.py
jwt_signature_validator/encoded_payload.py
jwt_signature_validator/py.typed
jwt_signature_validator/datastructures/__init__.py
jwt_signature_validator/exceptions/__init__.py
jwt_signature_validator/types/__init__.py
jwt_signature_validator-0.2.0.dist-info/METADATA
jwt_signature_validator-0.2.0.dist-info/WHEEL
jwt_signature_validator-0.2.0.dist-info/RECORD
