Metadata-Version: 2.4
Name: jwt-signature-validator
Version: 0.2.0
Summary: An ASGI Middleware to sign payload using JWT
Author-email: Irfanuddin Shafi Ahmed <irfanudeen08@gmail.com>
License-Expression: MIT
Classifier: Environment :: Web Environment
Classifier: Intended Audience :: Developers
Classifier: Operating System :: OS Independent
Classifier: Programming Language :: Python :: 3
Classifier: Programming Language :: Python :: 3.10
Classifier: Programming Language :: Python :: 3.11
Classifier: Programming Language :: Python :: 3.12
Classifier: Programming Language :: Python :: 3.13
Classifier: Programming Language :: Python :: Implementation :: CPython
Classifier: Programming Language :: Python :: Implementation :: PyPy
Classifier: Topic :: Internet :: WWW/HTTP
Requires-Python: >=3.10
Requires-Dist: fastapi>=0.128.0
Requires-Dist: pyjwt>=2.11.0
